{
  "page_title": "Gestion des Clients",
  "create_button": "Créer un Client",
  "table_logo": "Logo",
  "logo_create_info": "💡 Créez d'abord le client, puis vous pourrez ajouter un logo en l'éditant.",
  "table_name": "Nom",
  "table_email": "Email",
  "table_contact": "Contact",
  "table_phone": "Téléphone",
  "table_address": "Adresse",
  "modal_create_title": "Créer un Nouveau Client",
  "modal_edit_title": "Modifier le Client",
  "form_name": "Nom",
  "form_name_required": "Le nom est requis",
  "form_email": "Email",
  "form_contact": "Contact",
  "form_phone": "Téléphone",
  "form_address": "Adresse",
  "delete_confirm_message": "Êtes-vous sûr de vouloir supprimer ce client ?",
  "error_fetch": "Échec de la récupération des clients",
  "error_create": "Échec de la création du client",
  "error_update": "Échec de la mise à jour du client",
  "error_delete": "Échec de la suppression du client",
  "error_import": "Échec de l'importation des clients",
  "error_export": "Échec de l'exportation des clients",
  "success_create": "Client créé avec succès",
  "success_update": "Client mis à jour avec succès",
  "success_delete": "Client supprimé avec succès"
}
