{
  "page_title": "Gestion des politiques",
  "create_button": "Créer une politique",
  "import_button": "Importer",
  "export_button": "Exporter",
  "import_json": "Importer JSON",
  "import_csv": "Importer CSV",
  "export_json": "Exporter JSON",
  "export_csv": "Exporter CSV",
  "table_name": "Nom",
  "table_description": "Description",
  "table_permissions": "Permissions",
  "table_actions": "Actions",
  "no_policies": "Aucune politique",
  "modal_create_title": "Créer une politique",
  "modal_edit_title": "Éditer la politique",
  "form_name": "Nom",
  "form_name_required": "Nom *",
  "form_description": "Description",
  "form_cancel": "Annuler",
  "form_create": "Créer",
  "form_save": "Enregistrer",
  "permissions_modal_title": "Gérer les permissions",
  "permissions_select": "Sélectionner les permissions",
  "permissions_save": "Enregistrer",
  "operation_create": "Créer (CREATE)",
  "operation_read": "Lire (READ)",
  "operation_update": "Mettre à jour (UPDATE)",
  "operation_delete": "Supprimer (DELETE)",
  "delete_confirm_title": "Confirmer la suppression",
  "delete_confirm_message": "Êtes-vous sûr de vouloir supprimer cette politique ?",
  "delete_cancel": "Annuler",
  "delete_confirm": "Supprimer",
  "error_fetch": "Erreur lors de la récupération des données",
  "error_create": "Erreur lors de la création",
  "error_update": "Erreur lors de la mise à jour",
  "error_delete": "Erreur lors de la suppression",
  "error_export": "Erreur lors de l'export",
  "error_import": "Erreur lors de l'import",
  "import_report_title": "Rapport d'import",
  "import_report_close": "Fermer",
  "import_report_total": "Total",
  "import_report_success": "Succès",
  "import_report_failed": "Échecs",
  "import_report_errors": "Erreurs",
  "import_report_warnings": "Avertissements"
}
